get_aws_secret/__init__.py
get_aws_secret/constants.py
get_aws_secret-0.2.0b3.dist-info/LICENSE
get_aws_secret-0.2.0b3.dist-info/METADATA
get_aws_secret-0.2.0b3.dist-info/WHEEL
get_aws_secret-0.2.0b3.dist-info/top_level.txt
get_aws_secret-0.2.0b3.dist-info/RECORD
