Metadata-Version: 2.1
Name: get-aws-secret
Version: 0.2.0b3
Summary: Simplify retrieval of secrets from AWS SecretsManager. Optionally auto-memoize secrets in environment variables to improve performance and reduce costs.
Home-page: https://github.com/hacktlib/py-get-aws-secret/wiki
Author: Hackt.app
Author-email: opensource@hackt.app
License: UNKNOWN
Project-URL: Bug Reports, https://github.com/hacktlib/py-get-aws-secret/issues
Project-URL: Say Thanks!, http://lib.hackt.app
Project-URL: Source, https://github.com/hacktlib/py-get-aws-secret/
Platform: UNKNOWN
Classifier: Development Status :: 4 - Beta
Classifier: Intended Audience :: Developers
Classifier: License :: OSI Approved :: Apache Software License
Classifier: Natural Language :: English
Classifier: Programming Language :: Python :: 3
Classifier: Programming Language :: Python :: 3.6
Classifier: Programming Language :: Python :: 3.7
Classifier: Programming Language :: Python :: 3.8
Classifier: Programming Language :: Python :: 3 :: Only
Classifier: Topic :: Software Development :: Libraries
Classifier: Topic :: Utilities
Requires-Python: >=3.6, <4
Requires-Dist: boto3 (>=1.16.36)
Provides-Extra: dev
Requires-Dist: pytest (>=6.2.0) ; extra == 'dev'
Requires-Dist: coverage (>=5.3) ; extra == 'dev'
Requires-Dist: coverage-badge (>=1.0.1) ; extra == 'dev'
Requires-Dist: wheel (>=0.36.2) ; extra == 'dev'
Requires-Dist: flake8 (>=3.8.4) ; extra == 'dev'
Requires-Dist: autopep8 (>=1.5.4) ; extra == 'dev'
Provides-Extra: pub
Requires-Dist: pytest (>=6.2.0) ; extra == 'pub'
Requires-Dist: coverage (>=5.3) ; extra == 'pub'
Requires-Dist: coverage-badge (>=1.0.1) ; extra == 'pub'
Requires-Dist: wheel (>=0.36.2) ; extra == 'pub'
Requires-Dist: flake8 (>=3.8.4) ; extra == 'pub'
Requires-Dist: autopep8 (>=1.5.4) ; extra == 'pub'
Requires-Dist: twine (>=3.2.0) ; extra == 'pub'
